mailtool/__init__.py
mailtool/bridge.py
mailtool/cli.py
mailtool/mcp/__init__.py
mailtool/mcp/com_state.py
mailtool/mcp/exceptions.py
mailtool/mcp/lifespan.py
mailtool/mcp/models.py
mailtool/mcp/resources.py
mailtool/mcp/server.py
mailtool-0.10.0.dist-info/WHEEL
mailtool-0.10.0.dist-info/entry_points.txt
mailtool-0.10.0.dist-info/METADATA
mailtool-0.10.0.dist-info/RECORD
