Metadata-Version: 2.3
Name: mailtool
Version: 0.10.0
Summary: Outlook automation bridge for WSL2 via COM with MCP server for Claude Code
Keywords: outlook,com,automation,email,calendar,wsl2
Author: Sam
Author-email: Sam <s.mok@utwente.nl>
License: MIT
Classifier: Development Status :: 5 - Production/Stable
Classifier: Intended Audience :: Developers
Classifier: License :: OSI Approved :: MIT License
Classifier: Programming Language :: Python :: 3
Classifier: Programming Language :: Python :: 3.13
Classifier: Operating System :: Microsoft :: Windows
Classifier: Topic :: Office/Business :: Office Suites
Classifier: Topic :: Software Development :: Libraries :: Python Modules
Requires-Dist: pywin32>=306 ; sys_platform == 'win32'
Requires-Dist: mcp[cli]>=0.9.0
Requires-Python: >=3.13
